toon_parser-0.1.4.dist-info/METADATA
toon_parser-0.1.4.dist-info/WHEEL
toon_parser-0.1.4.dist-info/licenses/LICENSE
toon_parser/__init__.py
toon_parser/toon_parser.pyd
toon_parser-0.1.4.dist-info/RECORD
