Metadata-Version: 2.4
Name: toon-parser
Version: 0.1.4
Classifier: Development Status :: 4 - Beta
Classifier: Intended Audience :: Developers
Classifier: License :: OSI Approved :: MIT License
Classifier: License :: OSI Approved :: Apache Software License
Classifier: Programming Language :: Rust
Classifier: Programming Language :: Python :: 3
Classifier: Programming Language :: Python :: 3.8
Classifier: Programming Language :: Python :: 3.9
Classifier: Programming Language :: Python :: 3.10
Classifier: Programming Language :: Python :: 3.11
Classifier: Programming Language :: Python :: 3.12
Classifier: Programming Language :: Python :: Implementation :: CPython
Classifier: Programming Language :: Python :: Implementation :: PyPy
Classifier: Topic :: Software Development :: Libraries :: Python Modules
Classifier: Topic :: Text Processing
License-File: LICENSE
Summary: Fast Python bindings for TOON format parser
Keywords: toon,parser,serialization,performance
Author-email: magi8101 <sharmamagi0@gmail.com>
License: MIT OR Apache-2.0
Requires-Python: >=3.8
Project-URL: Homepage, https://github.com/magi8101/toon-parser
Project-URL: Repository, https://github.com/magi8101/toon-parser
Project-URL: Documentation, https://github.com/magi8101/toon-parser#readme
